descriptastorus/DescriptaStore.py
descriptastorus/MolFileIndex.py
descriptastorus/__init__.py
descriptastorus/append_store.py
descriptastorus/keyvalue.py
descriptastorus/make_store.py
descriptastorus/mode.py
descriptastorus/raw.py
descriptastorus/utils.py
descriptastorus/cli/__init__.py
descriptastorus/cli/storus.py
descriptastorus/cli/validate.py
descriptastorus/descriptors/DescriptorGenerator.py
descriptastorus/descriptors/QED.py
descriptastorus/descriptors/__init__.py
descriptastorus/descriptors/dists.py
descriptastorus/descriptors/hists.py
descriptastorus/descriptors/hists_v3.py
descriptastorus/descriptors/rdDescriptors.py
descriptastorus/descriptors/rdNormalizedDescriptors.py
descriptastorus/stores/__init__.py
descriptastorus/stores/dbmstore.py
descriptastorus/stores/kyotostore.py
descriptastorus-2.8.0.dist-info/LICENSE
descriptastorus-2.8.0.dist-info/METADATA
descriptastorus-2.8.0.dist-info/WHEEL
descriptastorus-2.8.0.dist-info/entry_points.txt
descriptastorus-2.8.0.dist-info/top_level.txt
descriptastorus-2.8.0.dist-info/RECORD
