Metadata-Version: 2.1
Name: descriptastorus
Version: 2.8.0
Summary: Descriptor creation, storage and molecular file indexing
Home-page: https://github/bp-kelley/descriptastorus
Author: Brian Kelley
Author-email: fustigator+descriptastorus@gmail.com
License-File: LICENSE
Requires-Dist: pandas-flavor
Requires-Dist: rdkit
Requires-Dist: scipy
Requires-Dist: numpy
